dagger/__init__.py
dagger/exceptions/__init__.py
dagger/exceptions/exceptions.py
dagger/executor/__init__.py
dagger/executor/executor.py
dagger/modeler/__init__.py
dagger/modeler/builder_helper.py
dagger/modeler/definition.py
dagger/service/__init__.py
dagger/service/engineconfig.py
dagger/service/services.py
dagger/store/__init__.py
dagger/store/stores.py
dagger/tasks/__init__.py
dagger/tasks/task.py
dagger/templates/__init__.py
dagger/templates/template.py
dagger/tracing/__init__.py
dagger/tracing/utils.py
dagger/utils/__init__.py
dagger/utils/utils.py
integration_tests/__init__.py
integration_tests/test_app.py
integration_tests/test_dagger.py
tests/__init__.py
tests/executor/__init__.py
tests/executor/test_executor.py
tests/modeler/__init__.py
tests/modeler/builder_helper_test.py
tests/modeler/test_definition.py
tests/service/__init__.py
tests/service/test_services.py
tests/store/__init__.py
tests/store/test_stores.py
tests/templates/__init__.py
tests/templates/test_template.py
tests/tracing/__init__.py
tests/tracing/test_utils.py
wf_dagger-0.2.6.dist-info/LICENSE
wf_dagger-0.2.6.dist-info/METADATA
wf_dagger-0.2.6.dist-info/WHEEL
wf_dagger-0.2.6.dist-info/top_level.txt
wf_dagger-0.2.6.dist-info/RECORD
