Metadata-Version: 2.1
Name: wf-dagger
Version: 0.2.6
Summary: Workflow Engine.
Home-page: https://github.com/wayfair-incubator/dagger
Author: Vikram Patki, Aditya Vaderiyettil
Author-email: vpatki@wayfair.com
Classifier: Development Status :: 4 - Beta
Classifier: Programming Language :: Python
Classifier: Programming Language :: Python :: 3
Classifier: Programming Language :: Python :: 3.7
Classifier: Programming Language :: Python :: 3.8
Classifier: Programming Language :: Python :: 3.9
Classifier: Programming Language :: Python :: 3.10
Classifier: License :: OSI Approved :: MIT License
Requires-Python: >=3.7
License-File: LICENSE
Requires-Dist: faust-streaming
